antichess/Agent.py
antichess/AntiChessGame.py
antichess/GameState.py
antichess/Piece.py
antichess/__init__.py
antichess-0.1.2.dist-info/LICENSE.txt
antichess-0.1.2.dist-info/METADATA
antichess-0.1.2.dist-info/WHEEL
antichess-0.1.2.dist-info/top_level.txt
antichess-0.1.2.dist-info/RECORD
