Metadata-Version: 2.1
Name: antichess
Version: 0.1.2
Summary: Package for simulating and playing antichess games.
Home-page: https://github.com/divitr/antichess
Author: Divit Rawal
Author-email: divit.rawal+antichess@gmail.com
License: UNKNOWN
Platform: UNKNOWN
Requires-Python: >=3.6
License-File: LICENSE.txt
Requires-Dist: numpy
